{
    "/js/backstage/index.js": "/js/backstage/index.js?id=5a383942a9ff4a61bee8",
    "/js/frontend/article.js": "/js/frontend/article.js?id=d936fd91fe0893e89c27",
    "/js/frontend/biglife.js": "/js/frontend/biglife.js?id=77cfd762ba7e30f8686f",
    "/js/frontend/contactus.js": "/js/frontend/contactus.js?id=56705eb9cc289cee3cd0",
    "/js/frontend/hospital.js": "/js/frontend/hospital.js?id=4be688e89dc51090ce37",
    "/js/frontend/index.js": "/js/frontend/index.js?id=451cede57eac3cd612d8",
    "/js/frontend/main.js": "/js/frontend/main.js?id=e42a2dc120c178807d8a",
    "/css/frontend/style.css": "/css/frontend/style.css?id=30a429259d92293df1ef",
    "/js/frontend/organization.js": "/js/frontend/organization.js?id=bec323fe0b49a7cb3136",
    "/js/frontend/product.js": "/js/frontend/product.js?id=1b4ec3665f3d03053a9e",
    "/js/frontend/product/oncovida.js": "/js/frontend/product/oncovida.js?id=b702b55f339d1885a977",
    "/js/frontend/product/oncovidl.js": "/js/frontend/product/oncovidl.js?id=0f7185f0f649ee10c05e",
    "/js/frontend/product/onpaca.js": "/js/frontend/product/onpaca.js?id=4e7ef8af35f417fa0ae0",
    "/js/frontend/product/onpakd.js": "/js/frontend/product/onpakd.js?id=97a8834ea63fce06b576",
    "/js/frontend/product/onpasn.js": "/js/frontend/product/onpasn.js?id=34a6666c2316a43ffbff",
    "/js/frontend/product/onta.js": "/js/frontend/product/onta.js?id=4f94bd1e16614554b692",
    "/js/frontend/product/ontadm.js": "/js/frontend/product/ontadm.js?id=3430b3434c38cd2f5bcb",
    "/js/frontend/product/ontaln.js": "/js/frontend/product/ontaln.js?id=883c30d48979df4a8044"
}
