{
    "/js/backstage/index.js": "/js/backstage/index.js?id=a480c98cb42be3efa9ef",
    "/js/frontend/amado.js": "/js/frontend/amado.js?id=6731081466c3327c8d54",
    "/js/frontend/article.js": "/js/frontend/article.js?id=d61cc7bd87b58419bae1",
    "/js/frontend/biglife.js": "/js/frontend/biglife.js?id=6ba9a5d61797d0118073",
    "/js/frontend/bloodtest.js": "/js/frontend/bloodtest.js?id=a7d8544da076db731173",
    "/js/frontend/claim.js": "/js/frontend/claim.js?id=608d96ab7177e9cec5bf",
    "/js/frontend/claim_detail.js": "/js/frontend/claim_detail.js?id=fe8749467fc2fa030012",
    "/js/frontend/contactus.js": "/js/frontend/contactus.js?id=dab67513fd5c1f011c2b",
    "/js/frontend/hospital.js": "/js/frontend/hospital.js?id=0906256f0fe49d64f448",
    "/js/frontend/index.js": "/js/frontend/index.js?id=5e4d4e7b32dffb9fedad",
    "/js/frontend/main.js": "/js/frontend/main.js?id=9246fb90412d59a6fd16",
    "/css/frontend/style.css": "/css/frontend/style.css?id=d2969be9789261bccefe",
    "/js/frontend/organization.js": "/js/frontend/organization.js?id=58972b851d371a48e623",
    "/js/frontend/policyenquiry.js": "/js/frontend/policyenquiry.js?id=1cf04968b3710f01c5d5",
    "/js/frontend/portallogin.js": "/js/frontend/portallogin.js?id=498757cf5c03dd9a490a",
    "/js/frontend/product.js": "/js/frontend/product.js?id=a30680accc38b940f15a",
    "/js/frontend/product/ci.js": "/js/frontend/product/ci.js?id=d21fd95edfb565906ffa",
    "/js/frontend/product/cvcare.js": "/js/frontend/product/cvcare.js?id=d401190fcd5566a14f0a",
    "/js/frontend/product/cvis22jan.js": "/js/frontend/product/cvis22jan.js?id=2fbfe4daef944537bb0d",
    "/js/frontend/product/cvisafe.js": "/js/frontend/product/cvisafe.js?id=8171f143999a4d95a155",
    "/js/frontend/product/diabetes.js": "/js/frontend/product/diabetes.js?id=83a55260354f904a2ca2",
    "/js/frontend/product/oncovida.js": "/js/frontend/product/oncovida.js?id=425404fe9b92872f378d",
    "/js/frontend/product/oncovidl.js": "/js/frontend/product/oncovidl.js?id=3b91815298633e25517f",
    "/js/frontend/product/oncovidmw.js": "/js/frontend/product/oncovidmw.js?id=5e49e7354a35033e1cc1",
    "/js/frontend/product/onfimp.js": "/js/frontend/product/onfimp.js?id=ea03ecc5bbb5fc5eb8f1",
    "/js/frontend/product/onmhs.js": "/js/frontend/product/onmhs.js?id=7ada4caca9bfaf2a29eb",
    "/js/frontend/product/onpaca.js": "/js/frontend/product/onpaca.js?id=ef7b8d956a97f05131e4",
    "/js/frontend/product/onpacaa.js": "/js/frontend/product/onpacaa.js?id=388ab2c06ba418a38b38",
    "/js/frontend/product/onpakd.js": "/js/frontend/product/onpakd.js?id=ec2df2a5bb8aafb78d1d",
    "/js/frontend/product/onpakda.js": "/js/frontend/product/onpakda.js?id=f18766b3386d4a203e9c",
    "/js/frontend/product/onpasn.js": "/js/frontend/product/onpasn.js?id=2652e76beaa547bba7da",
    "/js/frontend/product/onpasna.js": "/js/frontend/product/onpasna.js?id=e3b160404c641a95432a",
    "/js/frontend/product/onta.js": "/js/frontend/product/onta.js?id=163109ec0cd2ae645407",
    "/js/frontend/product/ontadm.js": "/js/frontend/product/ontadm.js?id=df20a7b68ff41c45bc16",
    "/js/frontend/product/ontaln.js": "/js/frontend/product/ontaln.js?id=db35f81b2654f8fca1b0",
    "/js/frontend/product/ontaob.js": "/js/frontend/product/ontaob.js?id=6e0b9df49cc786b4e316",
    "/js/frontend/product/ontgism.js": "/js/frontend/product/ontgism.js?id=c628b9366eae1e0f46c5",
    "/js/frontend/product/onvacina.js": "/js/frontend/product/onvacina.js?id=1d369c4cbde15f9bb616",
    "/js/frontend/product/onvs22jan.js": "/js/frontend/product/onvs22jan.js?id=ec9d89cde1b6b8583d77",
    "/js/frontend/product/onvsafe.js": "/js/frontend/product/onvsafe.js?id=f4b8a7b36387a9f64315",
    "/js/frontend/product/onvsafea.js": "/js/frontend/product/onvsafea.js?id=8eacb8059d8a7c522e16",
    "/js/frontend/product/onvsurea.js": "/js/frontend/product/onvsurea.js?id=9b2e8da6ca23c75a6a56",
    "/js/frontend/product/taipoct22.js": "/js/frontend/product/taipoct22.js?id=38a364f06d649f24ca69",
    "/js/frontend/product/taism.js": "/js/frontend/product/taism.js?id=57fcfb1b04782ba45f2d",
    "/js/frontend/product/taismtg.js": "/js/frontend/product/taismtg.js?id=bd77e4e529042f7bf55d",
    "/js/frontend/product/tgcvlp.js": "/js/frontend/product/tgcvlp.js?id=9ffc4ae65cea0d7c7c00",
    "/js/frontend/service.js": "/js/frontend/service.js?id=d136cdc98e8ee6f3471e",
    "/js/frontend/ta.js": "/js/frontend/ta.js?id=f196559e6b7d1093bc1c",
    "/js/frontend/taismtg.js": "/js/frontend/taismtg.js?id=8841a39d47d52ee84562",
    "/js/frontend/taxdeduction.js": "/js/frontend/taxdeduction.js?id=8ff6a7b2a8d832fde659",
    "/js/frontend/tg.js": "/js/frontend/tg.js?id=cfa4ac6c3c7b4f8e6b46",
    "/js/frontend/tgism.js": "/js/frontend/tgism.js?id=c6f15ae2cf083fef4cb2"
}
